setup.cfg
setup.py
asciinema/__init__.py
asciinema/__main__.py
asciinema/api.py
asciinema/asciicast.py
asciinema/config.py
asciinema/http_adapter.py
asciinema/player.py
asciinema/pty_recorder.py
asciinema/recorder.py
asciinema/stdout.py
asciinema/term.py
asciinema/urllib_http_adapter.py
asciinema/commands/__init__.py
asciinema/commands/auth.py
asciinema/commands/command.py
asciinema/commands/play.py
asciinema/commands/record.py
asciinema/commands/upload.py
codelynx.egg-info/PKG-INFO
codelynx.egg-info/SOURCES.txt
codelynx.egg-info/dependency_links.txt
codelynx.egg-info/entry_points.txt
codelynx.egg-info/top_level.txt